nomogram_explainer.py
nomogram_explainer-1.0.5.dist-info/METADATA
nomogram_explainer-1.0.5.dist-info/WHEEL
nomogram_explainer-1.0.5.dist-info/licenses/LICENSE
nomogram_explainer-1.0.5.dist-info/RECORD
