Metadata-Version: 2.4
Name: nomogram-explainer
Version: 1.0.5
Summary: Drawing the nomogram with python, and explain the model with nomogram-drived data
Author-email: Jeffery Liu <liuyp2080@gmail.com>
License: MIT
License-File: LICENSE
Classifier: License :: OSI Approved :: MIT License
Classifier: Operating System :: OS Independent
Classifier: Programming Language :: Python :: 3
Requires-Python: >=3.10
Requires-Dist: bokeh
Requires-Dist: lifelines
Requires-Dist: numpy
Requires-Dist: pandas
Requires-Dist: plotly
Requires-Dist: scikit-learn
Requires-Dist: statsmodels
